empyrionbuildassistant/__init__.py
empyrionbuildassistant/__main__.py
empyrionbuildassistant/BuildAssistant.py
empyrionbuildassistant/entry.py
empyrionbuildassistant/lib/__init__.py
empyrionbuildassistant-0.1.6.dist-info/entry_points.txt
empyrionbuildassistant-0.1.6.dist-info/LICENSE.txt
empyrionbuildassistant-0.1.6.dist-info/WHEEL
empyrionbuildassistant-0.1.6.dist-info/METADATA
empyrionbuildassistant-0.1.6.dist-info/RECORD
