Metadata-Version: 2.1
Name: empyrionbuildassistant
Version: 0.1.6
Summary: A simple set of scripts to make developing mods for Empyrion easier
Home-page: https://github.com/lostinplace/EmpyrionBuildAssistant
License: MIT
Author: Chris Wheeler
Author-email: cmwhee@gmail.com
Requires-Python: >=3.8,<4.0
Classifier: License :: OSI Approved :: MIT License
Classifier: Programming Language :: Python :: 3
Classifier: Programming Language :: Python :: 3.8
Requires-Dist: pathtools (>=0.1.2,<0.2.0)
Requires-Dist: psutil (>=5.7.0,<6.0.0)
Requires-Dist: vdf (>=3.2,<4.0)
Requires-Dist: watchdog (>=0.10.2,<0.11.0)
Project-URL: Repository, https://github.com/lostinplace/EmpyrionBuildAssistant
